minio/__init__.py
minio/api.py
minio/commonconfig.py
minio/datatypes.py
minio/deleteobjects.py
minio/error.py
minio/helpers.py
minio/legalhold.py
minio/lifecycleconfig.py
minio/minioadmin.py
minio/notificationconfig.py
minio/objectlockconfig.py
minio/replicationconfig.py
minio/retention.py
minio/select.py
minio/signer.py
minio/sse.py
minio/sseconfig.py
minio/tagging.py
minio/time.py
minio/versioningconfig.py
minio/xml.py
minio/credentials/__init__.py
minio/credentials/credentials.py
minio/credentials/providers.py
fano_oss_py_sdk-7.1.18.dist-info/LICENSE
fano_oss_py_sdk-7.1.18.dist-info/METADATA
fano_oss_py_sdk-7.1.18.dist-info/WHEEL
fano_oss_py_sdk-7.1.18.dist-info/top_level.txt
fano_oss_py_sdk-7.1.18.dist-info/RECORD
